<?xml version="1.0" encoding="utf-8" ?>
<Defs>
	<KCSG.StructureLayoutDef>
		<defName>VQE_Cryptoforge_Minefield_Alpha</defName>
		<tags>
			<li>VQE_Minefield</li>
		</tags>
		<spawnConduits>false</spawnConduits>
		<layouts>
			<li>
				<li>.,.,.,.,.,.,.,.,.,.,.,.,.,.,.,.,.,.,.,.,.,.,.</li>
				<li>.,.,.,.,.,.,.,.,.,.,.,.,.,.,.,.,.,.,.,.,.,.,.</li>
				<li>.,.,.,.,.,.,.,.,.,.,VQE_FrozenMinefieldSign,.,.,.,.,.,.,.,.,.,.,.,.</li>
				<li>.,.,.,.,.,.,.,.,.,.,.,.,.,.,.,.,.,.,VQE_AncientLandmine,.,.,.,.</li>
				<li>.,.,.,.,.,.,.,.,.,.,.,.,.,.,.,.,.,.,.,.,.,.,.</li>
				<li>.,.,.,.,.,.,.,.,.,.,.,.,VQE_AncientLandmine,.,.,.,.,.,.,.,.,.,.</li>
				<li>.,.,.,.,.,.,VQE_AncientLandmine,.,.,.,.,.,.,.,.,.,.,.,.,.,.,.,.</li>
				<li>.,.,.,.,.,.,.,.,.,.,.,.,.,.,.,.,.,.,.,.,.,.,.</li>
				<li>.,.,.,.,.,.,.,.,.,.,.,.,.,.,.,.,.,VQE_AncientLandmine,.,.,.,.,.</li>
				<li>.,.,.,.,.,.,.,.,.,.,.,.,.,.,.,.,.,.,.,.,.,.,.</li>
				<li>.,.,.,.,.,.,.,.,.,.,.,.,.,.,.,.,.,.,.,.,.,.,.</li>
				<li>.,.,.,.,.,.,.,.,.,.,.,.,.,.,.,.,.,.,.,.,.,.,.</li>
				<li>.,.,VQE_AncientLandmine,.,.,.,.,.,.,.,.,.,.,.,.,.,.,.,.,.,.,.,.</li>
				<li>.,.,.,.,.,.,.,.,.,.,.,.,VQE_AncientLandmine,.,.,.,.,.,.,.,.,.,.</li>
				<li>.,.,.,.,.,.,.,.,.,.,.,.,.,.,.,.,.,.,.,.,.,.,.</li>
				<li>.,.,.,.,.,.,.,.,.,.,.,.,.,.,.,.,.,.,VQE_AncientLandmine,.,.,.,.</li>
				<li>.,.,.,.,.,.,.,.,.,VQE_AncientLandmine,.,.,.,.,.,.,.,.,.,.,.,.,.</li>
				<li>.,.,.,.,.,.,.,.,.,.,.,.,.,.,.,.,.,.,.,.,.,.,.</li>
				<li>.,.,.,.,.,.,.,.,.,.,.,.,.,.,.,.,.,.,.,.,.,.,.</li>
				<li>.,.,.,.,.,.,.,.,.,.,.,.,.,.,.,.,.,.,VQE_FrozenMinefieldSign,.,.,.,.</li>
				<li>.,.,.,VQE_AncientLandmine,.,.,.,.,.,.,.,.,.,.,VQE_AncientLandmine,.,.,.,.,.,.,.,.</li>
				<li>.,.,.,.,.,.,.,.,.,.,.,.,.,.,.,.,.,.,.,.,.,.,.</li>
				<li>.,.,.,.,.,.,.,.,.,.,.,.,.,.,.,.,.,.,.,.,.,.,.</li>
			</li>
		</layouts>
		<modRequirements>
			<li>vanillaquestsexpanded.cryptoforge</li>
		</modRequirements>
	</KCSG.StructureLayoutDef>
	<KCSG.StructureLayoutDef>
		<defName>VQE_Cryptoforge_Minefield_Beta</defName>
		<tags>
			<li>VQE_Minefield</li>
		</tags>
		<spawnConduits>false</spawnConduits>
		<layouts>
			<li>
				<li>.,.,.,.,.,.,.,.,.,.,.,.,.,.,.,.,.,.,.,.,.,.,.</li>
				<li>.,.,.,.,.,.,.,.,.,.,.,.,.,.,.,.,.,.,.,.,.,.,.</li>
				<li>.,.,.,VQE_AncientLandmine,.,.,.,.,.,.,.,.,.,.,.,.,.,.,.,.,.,.,.</li>
				<li>.,.,.,.,.,.,.,.,.,.,.,.,.,.,.,.,.,.,.,VQE_AncientLandmine,.,.,.</li>
				<li>.,.,.,.,.,.,.,.,.,.,.,.,.,.,.,.,.,.,.,.,.,.,.</li>
				<li>.,.,.,.,.,.,.,.,.,VQE_AncientLandmine,.,.,.,.,.,.,VQE_FrozenMinefieldSign,.,.,.,.,.,.</li>
				<li>.,.,.,.,.,.,.,.,.,.,.,.,.,.,.,.,.,.,.,.,.,.,.</li>
				<li>.,.,.,.,.,.,.,.,.,VQE_AncientLandmine,.,.,.,.,.,.,.,.,.,.,.,.,.</li>
				<li>.,.,.,.,.,.,.,.,.,.,.,.,.,.,.,.,.,.,.,.,.,.,.</li>
				<li>.,.,.,VQE_AncientLandmine,.,.,.,.,.,.,.,.,.,.,.,.,.,.,.,VQE_AncientLandmine,.,.,.</li>
				<li>.,.,.,.,.,.,.,.,.,.,.,.,.,VQE_AncientLandmine,.,.,.,.,.,.,.,.,.</li>
				<li>.,.,.,.,.,.,.,.,.,.,.,.,.,.,.,.,.,.,.,.,.,.,.</li>
				<li>.,.,.,.,.,.,.,.,.,.,.,.,.,.,.,.,.,.,.,.,.,.,.</li>
				<li>.,.,.,.,.,.,.,.,.,.,.,.,.,.,.,.,.,.,.,.,.,.,.</li>
				<li>.,.,.,.,.,.,.,.,.,.,.,.,.,.,.,.,.,.,.,.,.,.,.</li>
				<li>.,.,.,.,.,VQE_AncientLandmine,.,.,.,.,.,.,.,.,.,.,.,VQE_AncientLandmine,.,.,.,.,.</li>
				<li>.,.,.,.,.,.,.,.,.,.,.,.,.,.,.,.,.,.,.,.,.,.,.</li>
				<li>.,.,.,.,.,.,.,.,.,.,.,.,.,.,.,.,.,.,.,.,.,.,.</li>
				<li>.,.,.,.,.,.,.,.,.,.,.,.,.,.,.,.,.,.,.,.,.,.,.</li>
				<li>.,.,.,.,.,.,.,.,.,.,.,.,VQE_AncientLandmine,.,.,.,.,.,.,.,.,.,.</li>
				<li>.,.,.,.,.,VQE_FrozenMinefieldSign,.,.,.,.,.,.,.,.,.,.,.,.,.,.,.,.,.</li>
				<li>.,.,.,.,.,.,.,.,.,.,.,.,.,.,.,.,.,.,.,.,.,.,.</li>
				<li>.,.,.,.,.,.,.,.,.,.,.,.,.,.,.,.,.,.,.,.,.,.,.</li>
			</li>
		</layouts>
		<modRequirements>
			<li>vanillaquestsexpanded.cryptoforge</li>
		</modRequirements>
	</KCSG.StructureLayoutDef>
	<KCSG.StructureLayoutDef>
		<defName>VQE_Cryptoforge_Minefield_Gamma</defName>
		<tags>
			<li>VQE_Minefield</li>
		</tags>
		<spawnConduits>false</spawnConduits>
		<layouts>
			<li>
				<li>.,.,.,.,.,.,.,.,.,.,.,.,.,.,.,.,.,.,.,.,.,.,.</li>
				<li>.,.,.,.,.,.,.,.,.,.,.,.,.,.,.,.,.,.,.,.,.,.,.</li>
				<li>.,.,.,.,.,.,.,.,.,.,.,.,.,.,.,.,.,.,.,.,VQE_AncientLandmine,.,.</li>
				<li>.,.,.,.,VQE_FrozenMinefieldSign,.,.,.,.,.,.,.,.,.,.,.,.,.,.,.,.,.,.</li>
				<li>.,.,.,VQE_AncientLandmine,.,.,.,.,.,.,.,.,.,.,.,.,.,.,.,.,.,.,.</li>
				<li>.,.,.,.,.,.,.,.,.,.,.,.,.,.,.,.,.,.,.,.,.,.,.</li>
				<li>.,.,.,.,.,.,.,.,VQE_AncientLandmine,.,.,.,.,.,.,VQE_AncientLandmine,.,.,.,.,.,.,.</li>
				<li>.,.,.,.,.,.,.,.,.,.,.,.,.,.,.,.,.,.,.,.,.,.,.</li>
				<li>.,.,.,.,.,.,.,.,.,.,.,.,.,.,.,.,.,.,.,.,.,.,.</li>
				<li>.,.,.,.,.,.,.,.,.,.,.,.,.,.,.,.,.,.,.,VQE_FrozenMinefieldSign,.,.,.</li>
				<li>.,.,.,.,VQE_AncientLandmine,.,.,.,.,.,.,.,.,.,.,.,.,.,.,.,.,.,.</li>
				<li>.,.,.,.,.,.,.,.,.,.,.,.,.,.,.,.,.,.,.,.,.,.,.</li>
				<li>.,.,.,.,.,.,.,.,.,.,.,.,VQE_AncientLandmine,.,.,.,.,.,.,VQE_AncientLandmine,.,.,.</li>
				<li>.,.,.,.,.,.,.,.,.,.,.,.,.,.,.,.,.,.,.,.,.,.,.</li>
				<li>.,.,.,.,.,.,.,.,.,.,.,.,.,.,.,.,.,.,.,.,.,.,.</li>
				<li>.,.,.,.,.,.,.,.,.,.,.,.,.,.,.,.,.,.,.,.,.,.,.</li>
				<li>.,.,.,VQE_AncientLandmine,.,.,.,.,.,.,.,.,.,.,.,.,.,.,.,.,.,.,.</li>
				<li>.,.,.,.,.,.,.,.,.,.,.,.,.,.,.,VQE_AncientLandmine,.,.,.,.,.,.,.</li>
				<li>.,.,.,.,.,.,.,.,.,.,.,.,.,.,.,.,.,.,.,.,.,.,.</li>
				<li>.,.,.,.,.,.,.,.,.,VQE_AncientLandmine,.,.,.,.,.,.,.,.,.,.,.,.,.</li>
				<li>.,.,.,.,.,.,.,.,.,.,.,.,.,.,.,.,.,.,.,.,.,.,.</li>
				<li>.,.,.,.,.,.,.,.,.,.,.,.,.,.,.,.,.,.,.,.,.,.,.</li>
				<li>.,.,.,.,.,.,.,.,.,.,.,.,.,.,.,.,.,.,.,.,.,.,.</li>
			</li>
		</layouts>
		<modRequirements>
			<li>vanillaquestsexpanded.cryptoforge</li>
		</modRequirements>
	</KCSG.StructureLayoutDef>
	<KCSG.StructureLayoutDef>
		<defName>VQE_Cryptoforge_Minefield_Delta</defName>
		<tags>
			<li>VQE_Minefield</li>
		</tags>
		<spawnConduits>false</spawnConduits>
		<layouts>
			<li>
				<li>.,.,VQE_AncientLandmine,.,.,.,.,.,.,.,.,.,.,.,.,.,.,.,.,.,.,.,.</li>
				<li>.,.,.,.,.,.,.,.,.,.,.,.,.,.,.,.,.,.,.,.,.,.,.</li>
				<li>.,.,.,.,.,.,.,.,.,.,.,.,.,.,.,.,.,.,.,.,.,.,.</li>
				<li>.,.,.,.,.,.,.,.,.,.,.,.,.,VQE_AncientLandmine,.,.,.,.,.,.,.,.,.</li>
				<li>.,.,.,.,.,.,.,.,VQE_AncientLandmine,.,.,.,.,.,.,.,.,.,.,.,.,.,.</li>
				<li>.,.,.,.,.,.,.,.,.,.,.,.,.,.,.,.,.,.,.,.,.,.,.</li>
				<li>.,.,.,.,.,.,.,.,.,.,.,.,.,.,.,.,.,.,.,.,.,.,.</li>
				<li>.,.,VQE_AncientLandmine,.,.,.,.,.,.,.,.,.,.,.,.,.,.,.,VQE_AncientLandmine,.,.,.,.</li>
				<li>.,.,.,.,.,.,.,.,.,.,.,.,.,.,.,.,.,.,.,VQE_FrozenMinefieldSign,.,.,.</li>
				<li>.,.,.,.,.,.,.,.,.,.,.,.,.,.,.,.,.,.,.,.,.,.,.</li>
				<li>.,.,.,.,.,.,.,.,.,.,.,.,.,.,.,.,.,.,.,.,.,.,.</li>
				<li>.,.,.,.,.,.,.,.,.,.,.,.,.,.,.,.,.,.,.,.,.,.,.</li>
				<li>.,.,.,.,.,.,.,.,.,.,.,.,.,.,.,.,.,.,.,.,.,.,.</li>
				<li>.,.,.,.,.,VQE_AncientLandmine,.,.,.,.,.,.,.,VQE_AncientLandmine,.,.,.,.,.,.,.,.,.</li>
				<li>.,.,.,.,.,.,.,.,.,.,.,.,.,.,.,.,.,.,.,.,.,.,.</li>
				<li>.,.,.,.,.,.,.,.,.,.,.,.,.,.,.,.,.,.,.,.,.,.,.</li>
				<li>.,.,.,.,.,.,.,.,.,.,.,.,.,.,.,.,.,.,.,.,.,.,.</li>
				<li>.,.,.,.,.,.,.,.,.,.,.,.,.,.,.,.,.,.,VQE_AncientLandmine,.,.,.,.</li>
				<li>.,.,VQE_AncientLandmine,.,.,.,.,.,.,.,.,.,.,.,.,.,.,.,.,.,.,.,.</li>
				<li>.,.,.,VQE_FrozenMinefieldSign,.,.,.,.,.,.,.,.,.,.,.,.,.,.,.,.,.,.,.</li>
				<li>.,.,.,.,.,.,.,.,.,VQE_AncientLandmine,.,.,.,.,.,.,.,.,.,.,.,.,.</li>
				<li>.,.,.,.,.,.,.,.,.,.,.,.,.,.,.,.,.,.,.,.,.,.,.</li>
				<li>.,.,.,.,.,.,.,.,.,.,.,.,.,.,.,.,.,.,.,.,.,.,.</li>
			</li>
		</layouts>
		<modRequirements>
			<li>vanillaquestsexpanded.cryptoforge</li>
		</modRequirements>
	</KCSG.StructureLayoutDef>
	<KCSG.StructureLayoutDef>
		<defName>VQE_Cryptoforge_Minefield_Epsilon</defName>
		<tags>
			<li>VQE_Minefield</li>
		</tags>
		<spawnConduits>false</spawnConduits>
		<layouts>
			<li>
				<li>.,.,.,.,.,.,.,.,.,.,.,.,.,.,.,.,.,.,.,.,.,.,.</li>
				<li>.,.,.,.,.,.,.,.,.,.,.,.,.,.,.,.,.,.,.,.,.,.,.</li>
				<li>.,.,.,.,.,.,.,.,.,.,.,.,.,.,.,.,.,.,.,.,VQE_AncientLandmine,.,.</li>
				<li>.,.,.,VQE_AncientLandmine,VQE_FrozenMinefieldSign,.,.,.,.,.,.,.,.,.,.,.,.,.,.,.,.,.,.</li>
				<li>.,.,.,.,.,.,.,.,.,.,.,.,.,.,.,.,.,.,.,.,.,.,.</li>
				<li>.,.,.,.,.,.,.,.,.,.,.,.,.,.,.,.,.,.,.,.,.,.,.</li>
				<li>.,.,.,.,.,.,.,.,.,.,.,VQE_AncientLandmine,.,.,.,.,.,.,.,.,.,.,.</li>
				<li>.,.,.,.,.,.,.,.,.,.,.,.,.,.,.,.,.,.,VQE_AncientLandmine,.,.,.,.</li>
				<li>.,.,.,.,.,.,.,.,.,.,.,.,.,.,.,.,.,.,.,.,.,.,.</li>
				<li>.,.,.,.,.,.,.,.,.,.,.,.,.,.,.,.,.,.,.,.,.,.,.</li>
				<li>.,.,.,.,.,VQE_AncientLandmine,.,.,.,.,.,.,.,.,.,.,.,.,.,.,.,.,.</li>
				<li>.,.,.,.,.,.,.,.,.,.,.,.,.,.,.,.,.,.,VQE_FrozenMinefieldSign,.,.,.,.</li>
				<li>.,.,.,.,.,.,.,.,.,.,.,.,.,.,.,.,.,.,.,.,.,VQE_AncientLandmine,.</li>
				<li>.,.,.,.,.,.,.,.,.,.,.,.,.,.,.,.,.,.,.,.,.,.,.</li>
				<li>.,.,.,.,.,.,.,.,.,.,VQE_AncientLandmine,.,.,.,.,.,.,.,.,.,.,.,.</li>
				<li>.,.,.,.,.,.,.,.,.,.,.,.,.,.,.,.,.,.,.,.,.,.,.</li>
				<li>.,.,.,.,.,.,.,.,.,.,.,.,.,.,.,.,.,.,.,.,.,.,.</li>
				<li>.,.,.,.,.,.,.,.,.,.,.,.,.,.,.,.,.,.,.,.,.,.,.</li>
				<li>.,.,.,.,.,.,.,.,.,.,.,.,.,.,.,.,.,.,.,.,.,.,.</li>
				<li>.,.,.,VQE_AncientLandmine,.,.,.,.,.,.,.,.,.,.,.,.,.,.,.,.,.,.,.</li>
				<li>.,.,.,.,.,.,.,.,.,.,.,.,.,.,.,.,.,.,.,.,VQE_AncientLandmine,.,.</li>
				<li>.,.,.,.,.,.,.,.,.,.,.,.,.,VQE_AncientLandmine,.,.,.,.,.,.,.,.,.</li>
				<li>.,.,.,.,.,.,.,.,.,.,.,.,.,.,.,.,.,.,.,.,.,.,.</li>
			</li>
		</layouts>
		<modRequirements>
			<li>vanillaquestsexpanded.cryptoforge</li>
		</modRequirements>
	</KCSG.StructureLayoutDef>
	<KCSG.StructureLayoutDef>
		<defName>VQE_Cryptoforge_Minefield_Zeta</defName>
		<tags>
			<li>VQE_Minefield</li>
		</tags>
		<spawnConduits>false</spawnConduits>
		<layouts>
			<li>
				<li>.,.,.,.,.,.,.,.,.,.,.,.,.,.,.,.,.,.,.,.,.,.,.</li>
				<li>.,.,.,.,.,.,.,.,.,.,.,.,.,.,VQE_AncientLandmine,.,.,.,.,.,.,.,.</li>
				<li>.,.,.,.,.,.,.,.,.,.,.,.,.,.,.,.,.,.,.,.,.,.,.</li>
				<li>.,.,.,.,.,.,.,.,.,.,.,.,.,.,.,.,.,.,.,.,VQE_AncientLandmine,.,.</li>
				<li>.,.,.,.,VQE_AncientLandmine,.,.,.,.,.,.,.,.,.,.,.,.,.,.,.,.,.,.</li>
				<li>.,.,.,.,.,.,.,.,.,.,.,.,.,.,.,.,.,.,.,.,.,.,.</li>
				<li>.,.,.,.,.,.,.,.,.,.,.,.,.,.,.,.,.,.,.,.,.,.,.</li>
				<li>.,.,.,.,.,.,.,.,.,.,.,.,.,.,.,.,VQE_AncientLandmine,.,.,.,.,.,.</li>
				<li>.,.,.,.,.,.,.,.,.,.,.,.,VQE_FrozenMinefieldSign,.,.,.,.,.,.,.,.,.,.</li>
				<li>.,.,.,.,.,.,.,.,VQE_AncientLandmine,.,.,.,.,.,.,.,.,.,.,.,.,.,.</li>
				<li>.,.,.,.,.,.,.,.,.,.,.,.,.,.,.,.,.,.,.,.,.,.,.</li>
				<li>.,.,.,.,.,.,.,.,.,.,.,.,.,.,.,.,.,.,.,.,.,.,.</li>
				<li>.,.,.,.,.,.,.,.,.,.,.,.,.,.,.,.,.,.,.,.,VQE_AncientLandmine,.,.</li>
				<li>.,.,.,.,.,.,.,.,.,.,.,.,.,.,.,.,.,.,.,.,.,.,.</li>
				<li>.,.,.,.,.,.,.,.,.,.,.,.,.,.,.,.,.,.,.,.,.,.,.</li>
				<li>.,.,.,.,.,.,.,.,VQE_AncientLandmine,.,.,.,.,.,.,.,.,.,.,.,.,.,.</li>
				<li>.,.,.,.,.,.,.,.,.,.,.,.,.,.,.,.,.,.,.,.,.,.,.</li>
				<li>.,.,.,.,.,.,.,.,.,.,.,.,.,.,.,.,.,.,VQE_AncientLandmine,.,.,.,.</li>
				<li>.,.,.,.,.,.,.,.,.,.,.,.,.,.,.,.,.,.,.,.,.,.,.</li>
				<li>.,.,.,.,.,.,.,.,.,.,.,.,VQE_AncientLandmine,.,.,.,.,.,.,.,.,.,.</li>
				<li>.,.,VQE_FrozenMinefieldSign,.,.,.,.,.,.,.,.,.,.,.,.,.,.,.,.,.,.,.,.</li>
				<li>.,.,.,.,.,.,.,.,.,.,.,.,.,.,.,.,.,.,.,.,.,VQE_AncientLandmine,.</li>
				<li>.,.,.,.,.,.,.,.,.,.,.,.,.,.,.,.,.,.,.,.,.,.,.</li>
			</li>
		</layouts>
		<modRequirements>
			<li>vanillaquestsexpanded.cryptoforge</li>
		</modRequirements>
	</KCSG.StructureLayoutDef>
	<KCSG.StructureLayoutDef>
		<defName>VQE_Cryptoforge_Minefield_Eta</defName>
		<tags>
			<li>VQE_Minefield</li>
		</tags>
		<spawnConduits>false</spawnConduits>
		<layouts>
			<li>
				<li>.,.,.,.,.,.,.,.,.,.,.,.,.,.,.,.,.,.,.,.,.,.,.</li>
				<li>.,.,.,.,.,.,.,.,.,.,.,.,.,.,.,.,.,.,.,.,.,VQE_AncientLandmine,.</li>
				<li>.,.,.,.,.,.,.,.,.,.,.,.,VQE_AncientLandmine,.,.,.,.,.,.,.,.,.,.</li>
				<li>.,.,.,.,.,.,.,.,.,.,.,.,.,.,VQE_FrozenMinefieldSign,.,.,.,.,.,.,.,.</li>
				<li>.,.,.,VQE_AncientLandmine,.,.,.,.,.,.,.,.,.,.,.,.,.,.,.,.,.,.,.</li>
				<li>.,.,.,.,.,.,.,.,.,.,.,.,.,.,.,.,.,VQE_AncientLandmine,.,.,.,.,.</li>
				<li>.,.,.,.,.,.,.,.,.,.,.,.,.,.,.,.,.,.,.,.,.,.,.</li>
				<li>.,.,.,.,.,.,.,.,.,.,.,.,.,.,.,.,.,.,.,.,.,.,.</li>
				<li>.,.,.,.,.,.,.,.,.,.,.,.,.,.,.,.,.,.,.,.,.,.,.</li>
				<li>.,.,.,.,.,.,.,.,.,.,VQE_AncientLandmine,.,.,.,.,.,.,.,.,.,.,.,.</li>
				<li>.,.,.,.,.,.,.,.,.,.,.,.,.,.,.,.,.,.,.,.,.,.,.</li>
				<li>.,.,VQE_AncientLandmine,.,.,.,.,.,.,.,.,.,.,.,.,.,.,.,.,.,.,.,.</li>
				<li>.,.,.,.,.,.,.,.,.,.,.,.,.,.,.,.,.,.,.,.,.,.,.</li>
				<li>.,.,.,.,.,VQE_FrozenMinefieldSign,.,.,.,.,.,.,.,.,.,.,.,.,.,.,.,.,.</li>
				<li>.,.,.,.,.,.,.,.,.,.,.,.,.,.,.,.,.,.,.,.,.,.,.</li>
				<li>.,.,.,.,.,.,.,.,.,.,.,.,.,.,.,.,.,.,.,.,.,.,.</li>
				<li>.,.,.,.,.,.,.,.,.,.,.,.,.,VQE_AncientLandmine,.,.,.,.,.,.,.,.,.</li>
				<li>.,.,.,.,.,.,.,.,.,.,.,.,.,.,.,.,.,.,.,.,.,.,.</li>
				<li>.,.,.,.,.,.,.,.,.,.,.,.,.,.,.,.,.,.,.,.,.,.,.</li>
				<li>.,.,.,VQE_AncientLandmine,.,.,.,.,.,.,.,.,.,.,.,.,.,VQE_FrozenMinefieldSign,.,.,VQE_AncientLandmine,.,.</li>
				<li>.,.,.,.,.,.,.,.,.,VQE_AncientLandmine,.,.,.,.,.,.,.,.,.,.,.,.,.</li>
				<li>.,.,.,.,.,.,.,.,.,.,.,.,.,.,.,.,.,.,.,.,.,.,.</li>
				<li>.,.,.,.,.,.,.,.,.,.,.,.,.,.,.,.,.,.,.,.,.,.,.</li>
			</li>
		</layouts>
		<modRequirements>
			<li>vanillaquestsexpanded.cryptoforge</li>
		</modRequirements>
	</KCSG.StructureLayoutDef>
	<KCSG.StructureLayoutDef>
		<defName>VQE_Cryptoforge_Minefield_Theta</defName>
		<tags>
			<li>VQE_Minefield</li>
		</tags>
		<spawnConduits>false</spawnConduits>
		<layouts>
			<li>
				<li>.,.,.,.,.,.,.,.,.,.,.,.,.,.,.,.,.,.,.,.,.,.,.</li>
				<li>.,.,.,.,.,.,.,.,.,.,.,.,.,.,.,.,.,.,.,.,.,.,.</li>
				<li>.,.,.,.,.,.,.,.,.,.,.,.,.,.,.,.,.,.,.,.,.,.,.</li>
				<li>.,.,.,.,.,.,.,.,.,.,.,.,.,.,.,.,.,.,.,VQE_FrozenMinefieldSign,.,.,.</li>
				<li>.,.,.,.,.,.,.,.,.,.,.,.,.,.,.,.,.,.,.,.,.,.,.</li>
				<li>.,.,.,VQE_AncientLandmine,.,.,.,.,.,.,.,.,.,.,.,.,.,.,.,.,.,.,.</li>
				<li>.,.,.,.,.,.,.,.,.,.,.,.,.,.,.,.,.,.,.,.,.,.,.</li>
				<li>.,.,.,.,.,.,.,.,.,.,.,.,.,.,.,.,.,.,.,.,VQE_AncientLandmine,.,.</li>
				<li>.,.,.,.,.,.,.,.,.,.,.,.,.,.,.,.,.,.,.,.,.,.,.</li>
				<li>.,.,.,.,.,.,.,.,.,.,.,.,.,.,.,.,.,.,.,.,.,.,.</li>
				<li>.,.,.,.,.,.,.,.,VQE_AncientLandmine,.,.,VQE_AncientLandmine,.,.,.,.,.,.,.,.,.,.,.</li>
				<li>.,.,.,.,.,.,.,.,.,.,.,.,.,.,.,.,VQE_AncientLandmine,.,.,.,.,.,.</li>
				<li>.,.,.,.,.,.,.,.,.,.,.,.,.,.,.,.,.,.,.,.,.,.,.</li>
				<li>.,.,.,.,.,.,.,.,.,.,.,.,VQE_FrozenMinefieldSign,.,.,.,.,.,.,.,.,.,.</li>
				<li>.,.,.,.,VQE_AncientLandmine,.,.,.,.,.,.,.,.,.,.,.,.,.,.,.,.,.,.</li>
				<li>.,.,.,.,.,.,.,.,.,.,.,.,.,.,.,.,.,.,.,.,.,.,.</li>
				<li>.,.,.,.,.,.,.,.,.,.,.,.,.,.,.,.,.,.,.,.,VQE_AncientLandmine,.,.</li>
				<li>.,.,.,.,.,.,.,.,.,.,.,.,.,.,.,.,.,.,.,.,.,.,.</li>
				<li>.,.,.,.,.,.,.,.,.,.,.,.,.,.,.,.,.,.,.,.,.,.,.</li>
				<li>.,.,.,.,.,.,.,.,.,VQE_AncientLandmine,.,.,.,.,.,.,.,.,.,.,.,.,.</li>
				<li>.,.,VQE_FrozenMinefieldSign,.,.,.,.,.,.,.,.,.,.,.,.,.,.,.,.,.,.,.,.</li>
				<li>.,.,.,.,.,.,.,.,.,.,.,.,.,.,.,VQE_AncientLandmine,.,.,.,.,.,.,.</li>
				<li>.,.,.,.,.,.,.,.,.,.,.,.,.,.,.,.,.,.,.,.,.,.,.</li>
			</li>
		</layouts>
		<modRequirements>
			<li>vanillaquestsexpanded.cryptoforge</li>
		</modRequirements>
	</KCSG.StructureLayoutDef>
	<KCSG.StructureLayoutDef>
		<defName>VQE_Cryptoforge_Minefield_Iota</defName>
		<tags>
			<li>VQE_Minefield</li>
		</tags>
		<spawnConduits>false</spawnConduits>
		<layouts>
			<li>
				<li>.,.,.,.,.,.,.,.,.,.,.,.,.,.,.,.,.,.,.,.,.,.,.</li>
				<li>.,.,.,.,.,.,.,.,.,.,.,.,.,.,.,.,.,.,.,.,.,.,.</li>
				<li>.,.,.,.,.,.,.,.,.,.,.,.,.,.,.,.,.,.,.,.,.,.,.</li>
				<li>.,.,.,.,.,.,.,VQE_AncientLandmine,.,.,.,.,.,.,.,.,.,.,.,.,.,.,.</li>
				<li>.,.,.,.,.,.,.,.,.,.,.,.,.,.,.,.,.,.,.,.,.,.,.</li>
				<li>.,.,.,.,.,.,.,.,.,.,.,.,.,.,.,.,.,.,.,.,.,.,.</li>
				<li>.,.,.,.,.,.,.,.,VQE_FrozenMinefieldSign,.,.,.,.,.,.,.,.,.,.,.,.,.,.</li>
				<li>.,.,.,.,.,.,.,.,.,.,.,.,.,.,.,.,.,.,.,.,.,.,.</li>
				<li>.,.,.,VQE_AncientLandmine,.,.,.,.,.,.,.,.,VQE_AncientLandmine,.,.,.,.,.,.,.,.,.,.</li>
				<li>.,.,.,.,.,.,.,.,.,.,.,.,.,.,.,.,.,.,.,.,.,.,.</li>
				<li>.,.,.,.,.,.,.,.,.,.,.,.,.,.,.,.,.,.,.,.,.,.,.</li>
				<li>.,.,.,.,.,.,.,.,.,.,.,.,.,.,.,.,.,.,.,.,.,.,.</li>
				<li>.,.,.,.,.,.,.,.,.,.,.,.,.,.,.,.,.,.,.,.,.,.,.</li>
				<li>.,.,.,.,.,.,VQE_AncientLandmine,.,.,.,.,.,.,.,.,.,.,.,.,.,.,.,.</li>
				<li>.,.,.,.,.,.,.,.,.,.,VQE_AncientLandmine,.,.,.,.,.,.,.,.,.,.,.,.</li>
				<li>.,.,.,.,.,.,.,.,.,.,.,.,.,.,.,.,.,VQE_AncientLandmine,.,.,.,.,.</li>
				<li>.,.,.,.,.,.,.,.,.,.,.,.,.,.,.,.,.,.,.,.,.,.,.</li>
				<li>.,.,.,VQE_AncientLandmine,.,.,.,.,.,.,.,.,.,.,.,.,.,.,.,.,.,.,.</li>
				<li>.,.,.,.,.,.,.,.,.,.,.,.,.,.,VQE_FrozenMinefieldSign,.,.,.,.,.,.,.,.</li>
				<li>.,.,.,.,.,.,.,.,.,.,.,.,.,.,.,.,.,.,.,.,.,.,.</li>
				<li>.,.,.,.,.,.,.,.,VQE_AncientLandmine,.,.,.,.,.,VQE_AncientLandmine,.,.,.,.,.,VQE_AncientLandmine,.,.</li>
				<li>.,.,.,.,.,.,.,.,.,.,.,.,.,.,.,.,.,.,.,.,.,.,.</li>
				<li>.,.,.,.,.,.,.,.,.,.,.,.,.,.,.,.,.,.,.,.,.,.,.</li>
			</li>
		</layouts>
		<modRequirements>
			<li>vanillaquestsexpanded.cryptoforge</li>
		</modRequirements>
	</KCSG.StructureLayoutDef>
	<KCSG.StructureLayoutDef>
		<defName>VQE_Cryptoforge_Minefield_Kappa</defName>
		<tags>
			<li>VQE_Minefield</li>
		</tags>
		<spawnConduits>false</spawnConduits>
		<layouts>
			<li>
				<li>.,.,.,.,.,.,.,.,.,.,.,.,.,.,.,.,.,.,.,.,.,.,.</li>
				<li>.,.,.,.,.,.,.,.,.,.,.,.,.,.,.,.,.,.,.,.,.,.,.</li>
				<li>.,.,.,.,.,.,.,.,.,.,.,.,.,.,.,.,.,.,VQE_AncientLandmine,.,.,.,.</li>
				<li>.,.,.,VQE_AncientLandmine,.,.,.,.,.,.,.,.,.,.,.,.,.,.,.,.,.,.,.</li>
				<li>.,.,.,.,.,.,.,.,.,.,.,.,.,.,.,.,.,.,.,VQE_FrozenMinefieldSign,.,.,.</li>
				<li>.,.,.,.,.,.,.,.,.,.,.,.,VQE_AncientLandmine,.,.,.,.,.,.,.,.,.,.</li>
				<li>.,.,.,.,.,.,.,.,.,.,.,.,.,.,.,.,.,.,.,.,.,.,.</li>
				<li>.,.,.,.,.,.,.,.,.,.,.,.,.,.,.,.,.,.,.,.,.,.,.</li>
				<li>.,.,.,.,.,.,.,.,.,.,.,.,.,.,.,.,.,.,.,.,VQE_AncientLandmine,.,.</li>
				<li>.,.,.,.,.,.,.,.,.,.,.,.,.,.,.,.,.,.,.,.,.,.,.</li>
				<li>.,.,.,.,.,.,.,VQE_FrozenMinefieldSign,.,.,.,.,.,.,.,.,.,.,.,.,.,.,.</li>
				<li>.,.,.,.,.,.,.,VQE_AncientLandmine,.,.,.,.,.,.,.,.,.,.,.,.,.,.,.</li>
				<li>.,.,.,.,.,.,.,.,.,.,.,.,.,.,.,VQE_AncientLandmine,.,.,.,.,.,.,.</li>
				<li>.,.,.,.,.,.,.,.,.,.,.,.,.,.,.,.,.,.,.,.,.,.,.</li>
				<li>.,.,.,.,.,.,.,.,.,.,.,.,.,.,.,.,.,.,.,.,.,.,.</li>
				<li>.,.,VQE_AncientLandmine,.,.,.,.,.,.,.,.,.,.,.,.,.,.,.,.,.,.,.,.</li>
				<li>.,.,.,.,.,.,.,.,.,.,.,.,.,.,.,.,.,.,.,VQE_AncientLandmine,.,.,.</li>
				<li>.,.,.,.,.,.,.,.,.,.,.,.,.,.,.,.,.,.,.,.,.,.,.</li>
				<li>.,.,.,.,.,.,.,.,.,.,.,.,.,.,.,.,.,.,.,.,.,.,.</li>
				<li>.,.,.,.,.,.,.,.,.,.,.,.,.,.,VQE_AncientLandmine,.,.,.,.,.,.,.,.</li>
				<li>.,.,.,.,.,.,.,.,.,.,.,.,.,.,.,.,.,.,.,.,VQE_AncientLandmine,.,.</li>
				<li>.,VQE_FrozenMinefieldSign,.,.,.,.,.,.,.,.,.,.,.,.,.,.,.,.,.,.,.,.,.</li>
				<li>.,.,.,.,.,.,.,.,.,.,.,.,.,.,.,.,.,.,.,.,.,.,.</li>
			</li>
		</layouts>
		<modRequirements>
			<li>vanillaquestsexpanded.cryptoforge</li>
		</modRequirements>
	</KCSG.StructureLayoutDef>
	<KCSG.StructureLayoutDef>
		<defName>VQE_Cryptoforge_Minefield_Lambda</defName>
		<tags>
			<li>VQE_Minefield</li>
		</tags>
		<spawnConduits>false</spawnConduits>
		<layouts>
			<li>
				<li>.,.,.,.,.,.,.,.,.,.,.,.,.,.,.,.,.,.,.,.,.,.,.</li>
				<li>.,.,.,.,.,.,.,.,.,.,.,.,.,.,.,.,.,.,.,.,.,.,.</li>
				<li>.,.,.,.,.,.,.,.,VQE_AncientLandmine,.,.,.,.,.,.,.,.,.,.,.,.,.,.</li>
				<li>.,.,.,.,.,.,.,.,.,.,.,.,.,.,.,.,.,.,.,.,.,.,.</li>
				<li>.,.,.,VQE_AncientLandmine,.,.,VQE_FrozenMinefieldSign,.,.,.,.,.,.,.,.,.,.,.,.,.,.,.,.</li>
				<li>.,.,.,.,.,.,.,.,.,.,.,.,.,.,.,.,.,.,VQE_AncientLandmine,.,.,.,.</li>
				<li>.,.,.,.,.,.,.,.,.,.,.,.,.,.,.,.,.,.,.,.,.,.,.</li>
				<li>.,.,.,.,.,.,.,.,.,.,.,.,.,.,.,.,.,.,.,.,.,.,.</li>
				<li>.,.,.,.,.,.,.,.,.,.,.,.,VQE_AncientLandmine,.,.,.,.,.,.,.,.,.,.</li>
				<li>.,.,.,.,.,.,.,.,.,.,.,.,.,.,.,.,.,.,.,.,.,.,.</li>
				<li>.,.,.,VQE_AncientLandmine,.,.,.,.,.,.,.,.,.,.,.,.,.,.,.,.,.,.,.</li>
				<li>.,.,.,.,.,.,.,.,.,.,.,.,.,.,.,.,.,.,.,.,.,.,.</li>
				<li>.,.,.,.,.,.,.,.,.,.,.,.,.,.,.,.,.,.,.,.,.,.,.</li>
				<li>.,.,.,.,.,.,.,.,.,.,.,.,.,.,.,.,.,.,.,.,.,.,.</li>
				<li>.,.,.,.,.,.,.,.,.,.,.,.,.,VQE_AncientLandmine,.,.,.,.,.,VQE_AncientLandmine,VQE_FrozenMinefieldSign,.,.</li>
				<li>.,.,.,.,.,.,.,.,.,.,.,.,.,.,.,.,.,.,.,.,.,.,.</li>
				<li>.,.,.,.,.,.,.,.,.,.,.,.,.,.,.,.,.,.,.,.,.,.,.</li>
				<li>.,.,.,.,.,.,.,.,.,.,.,.,.,.,.,.,.,.,.,.,.,.,.</li>
				<li>.,.,.,.,VQE_AncientLandmine,.,.,.,.,.,.,.,.,.,.,.,.,.,.,.,.,.,.</li>
				<li>.,.,.,.,.,.,.,.,.,.,.,.,VQE_AncientLandmine,.,.,.,.,.,.,.,.,.,.</li>
				<li>.,.,.,.,.,.,.,.,.,.,.,.,.,.,.,.,.,.,.,.,VQE_AncientLandmine,.,.</li>
				<li>.,.,.,.,.,.,.,.,.,.,.,.,.,.,.,.,.,.,.,.,.,.,.</li>
				<li>.,.,.,.,.,.,.,.,.,.,.,.,.,.,.,.,.,.,.,.,.,.,.</li>
			</li>
		</layouts>
		<modRequirements>
			<li>vanillaquestsexpanded.cryptoforge</li>
		</modRequirements>
	</KCSG.StructureLayoutDef>
	<KCSG.StructureLayoutDef>
		<defName>VQE_Cryptoforge_Minefield_Mu</defName>
		<tags>
			<li>VQE_Minefield</li>
		</tags>
		<spawnConduits>false</spawnConduits>
		<layouts>
			<li>
				<li>.,.,.,.,.,.,.,.,.,.,.,.,.,.,.,.,.,.,.,.,.,.,.</li>
				<li>.,.,.,.,.,.,.,.,.,.,.,.,.,.,.,.,.,.,.,.,.,.,.</li>
				<li>.,.,.,.,.,.,.,.,.,.,VQE_AncientLandmine,.,.,.,.,.,.,.,.,.,.,.,.</li>
				<li>.,.,.,.,.,.,.,.,.,.,.,.,.,.,.,.,.,.,.,.,.,.,.</li>
				<li>.,.,.,VQE_AncientLandmine,.,.,.,.,.,.,.,.,.,.,.,.,.,.,.,VQE_AncientLandmine,.,.,.</li>
				<li>.,.,.,.,.,.,.,.,.,.,VQE_FrozenMinefieldSign,.,.,.,.,.,.,.,.,.,.,.,.</li>
				<li>.,.,.,.,.,.,.,.,.,.,.,.,.,.,.,.,.,.,.,.,.,.,.</li>
				<li>.,.,.,.,.,.,.,.,.,.,.,.,.,.,.,.,VQE_AncientLandmine,.,.,.,.,.,.</li>
				<li>.,.,.,.,.,.,.,.,.,.,.,.,.,.,.,.,.,.,.,.,.,.,.</li>
				<li>.,.,.,.,.,.,.,.,VQE_AncientLandmine,.,.,.,.,.,.,.,.,.,.,.,.,.,.</li>
				<li>.,.,.,.,.,.,.,.,.,.,.,.,.,.,.,.,.,.,.,.,.,.,.</li>
				<li>.,.,.,.,.,.,.,.,.,.,.,.,.,.,.,.,.,.,.,.,.,.,.</li>
				<li>.,.,.,.,.,.,.,.,.,.,.,.,.,.,.,.,.,.,.,VQE_FrozenMinefieldSign,.,.,.</li>
				<li>.,.,.,VQE_AncientLandmine,.,.,.,.,.,.,.,.,.,.,.,.,.,.,.,.,.,.,.</li>
				<li>VQE_FrozenMinefieldSign,.,.,.,.,.,.,.,.,.,.,.,.,.,.,.,.,.,.,.,.,.,.</li>
				<li>.,.,.,.,.,.,.,.,.,.,.,.,.,.,VQE_AncientLandmine,.,.,.,.,.,.,.,.</li>
				<li>.,.,.,.,.,.,.,.,.,.,.,.,.,.,.,.,.,.,.,.,VQE_AncientLandmine,.,.</li>
				<li>.,.,.,.,.,.,.,.,.,.,.,.,.,.,.,.,.,.,.,.,.,.,.</li>
				<li>.,.,.,.,.,.,.,.,.,.,VQE_AncientLandmine,.,.,.,.,.,.,.,.,.,.,.,.</li>
				<li>.,.,.,.,.,.,.,.,.,.,.,.,.,.,.,.,.,VQE_AncientLandmine,.,.,.,.,.</li>
				<li>.,.,.,.,.,.,.,.,.,.,.,.,.,.,.,.,.,.,.,.,.,.,.</li>
				<li>.,.,.,.,.,.,.,.,.,.,.,.,.,.,.,.,.,.,.,.,.,.,.</li>
				<li>.,.,.,.,.,.,.,.,.,.,.,.,.,.,.,.,.,.,.,.,.,.,.</li>
			</li>
		</layouts>
		<modRequirements>
			<li>vanillaquestsexpanded.cryptoforge</li>
		</modRequirements>
	</KCSG.StructureLayoutDef>
	<KCSG.StructureLayoutDef>
		<defName>VQE_Cryptoforge_Minefield_Nu</defName>
		<tags>
			<li>VQE_Minefield</li>
		</tags>
		<spawnConduits>false</spawnConduits>
		<layouts>
			<li>
				<li>.,.,.,.,.,.,.,.,.,.,.,.,.,.,.,.,.,.,.,.,.,.,.</li>
				<li>.,.,.,.,.,.,.,.,.,.,.,.,.,.,.,.,.,.,.,.,.,.,.</li>
				<li>.,.,.,.,.,.,.,.,.,.,.,.,.,.,.,.,.,.,.,.,.,.,.</li>
				<li>.,.,.,.,.,VQE_AncientLandmine,.,.,.,.,VQE_FrozenMinefieldSign,.,.,.,.,.,.,.,.,VQE_AncientLandmine,.,.,.</li>
				<li>.,.,.,.,.,.,.,.,.,.,.,.,VQE_AncientLandmine,.,.,.,.,.,.,.,.,.,.</li>
				<li>.,.,.,.,.,.,.,.,.,.,.,.,.,.,.,.,.,.,.,.,.,.,.</li>
				<li>.,.,.,.,.,.,.,.,.,.,.,.,.,.,.,.,.,.,.,.,.,.,.</li>
				<li>.,.,VQE_AncientLandmine,.,.,.,.,.,.,.,.,.,.,.,.,.,.,.,.,.,.,.,.</li>
				<li>.,VQE_FrozenMinefieldSign,.,.,.,.,.,.,.,.,.,.,.,.,.,.,.,.,.,.,.,.,.</li>
				<li>.,.,.,.,.,.,.,.,.,.,.,.,.,.,.,.,.,.,.,.,.,.,.</li>
				<li>.,.,.,.,.,.,VQE_AncientLandmine,.,.,.,.,.,.,.,.,.,VQE_AncientLandmine,.,.,.,.,.,.</li>
				<li>.,.,.,.,.,.,.,.,.,.,.,.,.,.,.,.,.,.,.,.,.,.,.</li>
				<li>.,.,.,.,.,.,.,.,.,.,.,.,.,.,.,.,.,.,.,.,.,.,.</li>
				<li>.,.,.,.,.,.,.,.,.,.,.,.,.,.,.,.,.,.,.,.,.,.,.</li>
				<li>.,.,.,.,.,.,.,.,.,.,.,.,.,.,.,.,.,.,.,.,.,.,.</li>
				<li>.,.,.,.,.,.,.,.,.,.,.,.,.,.,.,.,.,.,.,.,.,.,.</li>
				<li>.,.,.,.,.,.,.,.,.,.,.,.,.,VQE_AncientLandmine,.,.,.,.,.,.,.,.,.</li>
				<li>.,.,.,VQE_AncientLandmine,.,.,.,.,.,.,.,.,.,.,.,.,.,.,.,.,.,.,.</li>
				<li>.,.,.,.,.,.,.,.,.,.,.,.,.,.,.,.,.,.,.,.,.,.,.</li>
				<li>.,.,.,.,.,.,.,.,VQE_AncientLandmine,.,.,.,.,.,.,.,.,.,VQE_AncientLandmine,.,.,.,.</li>
				<li>.,.,.,.,.,.,.,.,.,.,.,.,.,.,.,.,.,.,.,VQE_FrozenMinefieldSign,.,.,.</li>
				<li>.,.,.,.,.,.,.,.,.,.,.,.,.,.,.,.,.,.,.,.,.,.,.</li>
				<li>.,.,.,.,.,.,.,.,.,.,.,.,.,.,.,.,.,.,.,.,.,.,.</li>
			</li>
		</layouts>
		<modRequirements>
			<li>vanillaquestsexpanded.cryptoforge</li>
		</modRequirements>
	</KCSG.StructureLayoutDef>
	<KCSG.StructureLayoutDef>
		<defName>VQE_Cryptoforge_Minefield_Xi</defName>
		<tags>
			<li>VQE_Minefield</li>
		</tags>
		<spawnConduits>false</spawnConduits>
		<layouts>
			<li>
				<li>.,.,.,.,.,.,.,.,.,.,.,.,.,.,.,.,.,.,.,.,.,.,.</li>
				<li>.,.,.,.,.,.,.,.,.,.,.,.,.,.,.,.,.,.,.,.,.,.,.</li>
				<li>.,.,.,.,.,.,.,.,.,.,.,.,.,.,.,.,.,.,.,.,.,.,.</li>
				<li>.,.,.,.,.,.,.,.,.,.,.,.,.,.,.,.,.,.,.,.,.,.,.</li>
				<li>.,.,.,.,.,.,.,.,.,.,.,.,.,.,.,.,.,.,.,.,.,.,.</li>
				<li>.,.,.,.,.,.,.,.,.,.,.,.,VQE_AncientLandmine,.,.,.,.,.,.,.,.,.,.</li>
				<li>.,.,.,.,.,.,.,.,.,.,.,.,.,.,.,.,.,.,.,.,.,.,.</li>
				<li>.,.,.,VQE_AncientLandmine,.,.,.,.,.,.,.,.,.,.,VQE_FrozenMinefieldSign,.,.,.,.,.,.,.,.</li>
				<li>.,.,.,.,.,.,.,.,.,.,.,.,.,.,.,.,.,.,.,.,.,.,.</li>
				<li>.,.,.,.,.,.,.,.,.,.,.,.,.,.,.,.,.,.,.,.,.,.,.</li>
				<li>.,.,.,.,.,.,.,.,.,.,.,.,.,.,.,.,.,.,.,.,.,.,.</li>
				<li>.,.,.,.,.,.,.,.,.,.,VQE_AncientLandmine,.,.,.,.,.,.,.,.,.,.,.,.</li>
				<li>.,.,.,VQE_AncientLandmine,.,.,.,.,.,.,.,.,.,.,.,.,.,.,.,.,.,.,.</li>
				<li>.,.,.,.,.,.,.,.,.,.,.,.,.,.,.,.,.,.,.,.,.,.,.</li>
				<li>.,.,.,.,.,.,.,.,.,.,.,.,.,.,.,.,.,.,.,.,.,.,.</li>
				<li>.,.,.,.,.,.,.,.,VQE_AncientLandmine,.,.,.,.,.,.,.,.,.,.,.,.,.,.</li>
				<li>.,.,.,.,.,.,.,.,.,.,.,.,.,.,.,.,VQE_AncientLandmine,.,.,.,.,.,.</li>
				<li>.,.,.,.,.,.,.,.,.,.,.,.,.,.,.,.,.,.,.,.,.,.,.</li>
				<li>.,.,VQE_AncientLandmine,.,.,.,.,.,.,.,.,.,.,.,.,.,.,.,.,.,.,.,.</li>
				<li>.,.,.,.,.,.,.,.,.,.,.,.,VQE_AncientLandmine,.,.,.,.,.,.,.,.,.,.</li>
				<li>.,.,VQE_FrozenMinefieldSign,.,.,.,VQE_AncientLandmine,.,.,.,.,.,.,.,.,.,.,.,.,VQE_AncientLandmine,.,.,.</li>
				<li>.,.,.,.,.,.,.,.,.,.,.,.,.,.,.,.,.,.,.,.,.,.,.</li>
				<li>.,.,.,.,.,.,.,.,.,.,.,.,.,.,.,.,.,.,.,.,.,.,.</li>
			</li>
		</layouts>
		<modRequirements>
			<li>vanillaquestsexpanded.cryptoforge</li>
		</modRequirements>
	</KCSG.StructureLayoutDef>
</Defs>